wattrex_battery_cycler/app/app_man/__init__.py
wattrex_battery_cycler/app/app_man/app_man_core.py
wattrex_battery_cycler/app/app_man/app_man_node.py
wattrex_battery_cycler/app/app_man/context.py
wattrex_battery_cycler/mid/mid_dabs/__init__.py
wattrex_battery_cycler/mid/mid_dabs/context.py
wattrex_battery_cycler/mid/mid_dabs/mid_dabs.py
wattrex_battery_cycler/mid/mid_meas/__init__.py
wattrex_battery_cycler/mid/mid_meas/context.py
wattrex_battery_cycler/mid/mid_meas/mid_meas.py
wattrex_battery_cycler/mid/mid_pwr/__init__.py
wattrex_battery_cycler/mid/mid_pwr/mid_pwr.py
wattrex_battery_cycler/mid/mid_str/__init__.py
wattrex_battery_cycler/mid/mid_str/context.py
wattrex_battery_cycler/mid/mid_str/mid_str_cmd.py
wattrex_battery_cycler/mid/mid_str/mid_str_facade.py
wattrex_battery_cycler/mid/mid_str/mid_str_mapping.py
wattrex_battery_cycler/mid/mid_str/mid_str_node.py
wattrex_battery_cycler-1.0.3.dist-info/LICENSE.txt
wattrex_battery_cycler-1.0.3.dist-info/METADATA
wattrex_battery_cycler-1.0.3.dist-info/WHEEL
wattrex_battery_cycler-1.0.3.dist-info/top_level.txt
wattrex_battery_cycler-1.0.3.dist-info/RECORD
